OntologyToAPI/__init__.py
OntologyToAPI/core/APIGenerator.py
OntologyToAPI/core/Ontology.py
OntologyToAPI/core/Queries.py
OntologyToAPI/core/Utility.py
OntologyToAPI/core/__init__.py
OntologyToAPI/core/Connectors/IndentifyConnector.py
OntologyToAPI/core/Connectors/__init__.py
OntologyToAPI/core/Connectors/Stateful/SocketConnection.py
OntologyToAPI/core/Connectors/Stateful/__init__.py
OntologyToAPI/core/Connectors/Stateless/APIConnection.py
OntologyToAPI/core/Connectors/Stateless/MYSQLConnection.py
OntologyToAPI/core/Connectors/Stateless/MongoDBConnection.py
OntologyToAPI/core/Connectors/Stateless/POSTGRESQLConnection.py
OntologyToAPI/core/Connectors/Stateless/SQLITEConnection.py
OntologyToAPI/core/Connectors/Stateless/UNQLITEConnection.py
OntologyToAPI/core/Connectors/Stateless/__init__.py
OntologyToAPI/core/DTO/BusinessModel.py
OntologyToAPI/core/DTO/ExternalCode.py
OntologyToAPI/core/DTO/Metadata.py
OntologyToAPI/core/DTO/Source.py
OntologyToAPI/core/DTO/__init__.py
Settings/__init__.py
ontologytoapi-0.0.19.dist-info/licenses/LICENSE
ontologytoapi-0.0.19.dist-info/METADATA
ontologytoapi-0.0.19.dist-info/WHEEL
ontologytoapi-0.0.19.dist-info/top_level.txt
ontologytoapi-0.0.19.dist-info/RECORD
