Metadata-Version: 2.4
Name: ontologytoapi
Version: 0.0.19
Summary: Multi purpose API Generator based on an Ontology Framework.
Home-page: https://github.com/JCGCosta/OntologyToAPI
Author: Júlio César Guimarães Costa
Author-email: juliocesargcosta123@gmail.com
License: MIT License
Keywords: Ontology,API
Classifier: Development Status :: 3 - Alpha
Classifier: Intended Audience :: Developers
Classifier: Operating System :: Microsoft :: Windows :: Windows 11
Classifier: License :: OSI Approved :: MIT License
Classifier: Topic :: Software Development :: Libraries :: Python Modules
Classifier: Programming Language :: Python :: 3.11
License-File: LICENSE
Requires-Dist: SQLAlchemy
Requires-Dist: pydantic
Requires-Dist: requests
Requires-Dist: pymongo
Requires-Dist: rdflib
Requires-Dist: fastapi
Requires-Dist: uvicorn
Requires-Dist: python-multipart
Requires-Dist: asyncio
Requires-Dist: unqlite
Requires-Dist: asyncpg
Requires-Dist: aiomysql
Requires-Dist: aiosqlite
Requires-Dist: motor
Requires-Dist: aiofiles
Dynamic: author
Dynamic: author-email
Dynamic: classifier
Dynamic: description
Dynamic: description-content-type
Dynamic: home-page
Dynamic: keywords
Dynamic: license
Dynamic: license-file
Dynamic: requires-dist
Dynamic: summary
